osc2mqtt.py
osc2mqtt/util.py
osc2mqtt/__init__.py
osc2mqtt/converter.py
osc2mqtt/__main__.py
osc2mqtt/lru_cache.py
osc2mqtt-0.2b2.dist-info/top_level.txt
osc2mqtt-0.2b2.dist-info/entry_points.txt
osc2mqtt-0.2b2.dist-info/RECORD
osc2mqtt-0.2b2.dist-info/DESCRIPTION.rst
osc2mqtt-0.2b2.dist-info/METADATA
osc2mqtt-0.2b2.dist-info/zip-safe
osc2mqtt-0.2b2.dist-info/WHEEL
osc2mqtt-0.2b2.dist-info/metadata.json
