Metadata-Version: 2.0
Name: osc2mqtt
Version: 0.2b2
Summary: An OSC to MQTT bridge based on pyliblo and paho-mqtt.
Home-page: https://github.com/SpotlightKid/osc2mqtt
Author: Christopher Arndt
Author-email: chris@chrisarndt.de
License: MIT License
Download-URL: https://github.com/SpotlightKid/osc2mqtt/releases
Keywords: osc mqtt iot
Platform: POSIX
Platform: Windows
Platform: MacOS X
Classifier: Development Status :: 4 - Beta
Classifier: Environment :: Console
Classifier: Intended Audience :: Developers
Classifier: Intended Audience :: End Users/Desktop
Classifier: Intended Audience :: Manufacturing
Classifier: Intended Audience :: Other Audience
Classifier: License :: OSI Approved :: MIT License
Classifier: Operating System :: Microsoft :: Windows
Classifier: Operating System :: POSIX
Classifier: Operating System :: MacOS :: MacOS X
Classifier: Programming Language :: Python
Classifier: Programming Language :: Python :: 2.7
Classifier: Programming Language :: Python :: 3.3
Classifier: Programming Language :: Python :: 3.4
Classifier: Topic :: Communications
Classifier: Topic :: Internet
Classifier: Topic :: Home Automation
Classifier: Topic :: Multimedia :: Sound/Audio
Requires-Dist: paho-mqtt
Requires-Dist: pyliblo
